hoangk7/__init__.py
hoangk7/hi.py
hoangk7/hoang.py
hoangk7/ok.py
hoangk7-0.0.0.dist-info/METADATA
hoangk7-0.0.0.dist-info/WHEEL
hoangk7-0.0.0.dist-info/top_level.txt
hoangk7-0.0.0.dist-info/RECORD
