Metadata-Version: 2.1
Name: hoangk7
Version: 0.0.0
Summary: test upload by hoang
Author: Hoang lt
Author-email: kodzhoang@gmail.com
Keywords: hoangk7,hoang,hoanglt
Requires-Python: >=3.10
Requires-Dist: requests
